MANIFEST.in
README.md
VERSION.txt
requirements.txt
setup.py
account_management/__init__.py
account_management/admin.py
account_management/apps.py
account_management/forms.py
account_management/lib.py
account_management/models.py
account_management/tests.py
account_management/urls.py
account_management/views.py
account_management/migrations/0001_initial.py
account_management/migrations/__init__.py
django_mxio_account_management.egg-info/PKG-INFO
django_mxio_account_management.egg-info/SOURCES.txt
django_mxio_account_management.egg-info/dependency_links.txt
django_mxio_account_management.egg-info/not-zip-safe
django_mxio_account_management.egg-info/top_level.txt
testproject/__init__.py
testproject/asgi.py
testproject/lib.py
testproject/settings.py
testproject/urls.py
testproject/views.py
testproject/wsgi.py