Metadata-Version: 1.0
Name: django-mxio-account-management
Version: 1.0.1
Summary: Custom account management functionality for Django
Home-page: https://matix.io
Author: Connor Bode
Author-email: connor@matix.io
License: MIT
Platform: UNKNOWN
